{
	"2014-2-1":{
		"gameid": "2014-2-1",
		"year": 2014,
		"season": 2,
		"game": 1,
		"name": "Kaitlyn",
		"snack": "Gummy Candies and Beer Nuts"
	},
	"2014-2-2":{
		"gameid": "2014-2-2",
		"year": 2014,
		"season": 2,
		"game": 2,
		"name": "Tratham",
		"snack": "Timbits"
	},
	"2014-2-3":{
		"gameid": "2014-2-3",
		"year": 2014,
		"season": 2,
		"game": 3,
		"name": "Jeff",
		"snack": "Rice Krispie Squares and Granola Bars"
	},
	"2014-2-4":{
		"gameid": "2014-2-4",
		"year": 2014,
		"season": 2,
		"game": 4,
		"name": "Katia",
		"snack": "Sausages and Cheese"
	},
	"2014-2-5":{
		"gameid": "2014-2-5",
		"year": 2014,
		"season": 2,
		"game": 5,
		"name": "Andy",
		"snack": "Pepperettes, Freezies and Berries"
	},
	"2014-2-6":{
		"gameid": "2014-2-6",
		"year": 2014,
		"season": 2,
		"game": 6,
		"name": "Tom",
		"snack": "Watermelon and Turkey Sausage"
	},
	"2014-2-7":{
		"gameid": "2014-2-7",
		"year": 2014,
		"season": 2,
		"game": 7,
		"name": "Stuart",
		"snack": "Fruit Tray and Donuts"
	},
	"2014-3-1":{
		"gameid": "2014-3-1",
		"year": 2014,
		"season": 3,
		"game": 1,
		"name": "Kim",
		"snack": "Frozen Fruit Skewers"
	},
	"2014-3-2":{
		"gameid": "2014-3-2",
		"year": 2014,
		"season": 3,
		"game": 2,
		"name": "Lou",
		"snack": "Rice Krispie Squares and Granola Bars"
	},
	"2014-3-3":{
		"gameid": "2014-3-3",
		"year": 2014,
		"season": 3,
		"game": 3,
		"name": "Garrett",
		"snack": "Sausages, Cheese and Cherries"
	},
	"2014-3-4":{
		"gameid": "2014-3-4",
		"year": 2014,
		"season": 3,
		"game": 4,
		"name": "Charles",
		"snack": "Timbits and Cold Drinks"
	},
	"2014-3-5":{
		"gameid": "2014-3-5",
		"year": 2014,
		"season": 3,
		"game": 5,
		"name": "Annie",
		"snack": "Mini Chocolate Chip Cookies"
	},
	"2014-3-6":{
		"gameid": "2014-3-6",
		"year": 2014,
		"season": 3,
		"game": 6,
		"name": "Brookes",
		"snack": "Timbits"
	},
	"2014-3-7":{
		"gameid": "2014-3-7",
		"year": 2014,
		"season": 3,
		"game": 7,
		"name": "Albert",
		"snack": "Frozen Grapes and Homemade Cookies"
	},
	"2014-3-8":{
		"gameid": "2014-3-8",
		"year": 2014,
		"season": 3,
		"game": 8,
		"name": "Michelle",
		"snack": ""
	},
	"2015-2-1":{
		"gameid": "2015-2-1",
		"year": 2015,
		"season": 2,
		"game": 1,
		"name": "Lou",
		"snack": "Mini Birthday Cupcakes"
	},
	"2015-2-2":{
		"gameid": "2015-2-2",
		"year": 2015,
		"season": 2,
		"game": 2,
		"name": "Katia",
		"snack": "Cheese Cubes and Crackers"
	},
	"2015-2-3":{
		"gameid": "2015-2-3",
		"year": 2015,
		"season": 2,
		"game": 3,
		"name": "Albert",
		"snack": "Assorted Chips"
	},
	"2015-2-4":{
		"gameid": "2015-2-4",
		"year": 2015,
		"season": 2,
		"game": 4,
		"name": "Michelle",
		"snack": "Rice Krispie Squares"
	},
	"2015-2-5":{
		"gameid": "2015-2-5",
		"year": 2015,
		"season": 2,
		"game": 5,
		"name": "Annie",
		"snack": "Chocolate Pop-Tarts"
	},
	"2015-2-7":{
		"gameid": "2015-2-7",
		"year": 2015,
		"season": 2,
		"game": 7,
		"name": "Kaitlyn",
		"snack": "Timbits"
	},
	"2015-3-2":{
		"gameid": "2015-3-2",
		"year": 2015,
		"season": 3,
		"game": 2,
		"name": "Jeff",
		"snack": "Freezies"
	},
	"2015-3-4":{
		"gameid": "2015-3-4",
		"year": 2015,
		"season": 3,
		"game": 4,
		"name": "Nathan",
		"snack": "Fruit Roll-Ups & Granola Bars"
	}
}